verysimplemodule_romuere/__init__.py
verysimplemodule_romuere/add.py
verysimplemodule_romuere/subtract.py
verysimplemodule_romuere/extra/__init__.py
verysimplemodule_romuere/extra/divide.py
verysimplemodule_romuere/extra/multiple.py
verysimplemodule_romuere-0.0.5.dist-info/METADATA
verysimplemodule_romuere-0.0.5.dist-info/WHEEL
verysimplemodule_romuere-0.0.5.dist-info/top_level.txt
verysimplemodule_romuere-0.0.5.dist-info/RECORD
