Metadata-Version: 2.1
Name: verysimplemodule-romuere
Version: 0.0.5
Summary: My first Python package
Author: romuere
Author-email: romuere@ufpi.edu.br
Keywords: python,first package
Classifier: Development Status :: 3 - Alpha
Classifier: Intended Audience :: Education
Classifier: Programming Language :: Python :: 3
Classifier: Operating System :: OS Independent
Requires-Dist: scikit-image
Requires-Dist: numpy
